odoo_mcp/__init__.py
odoo_mcp/cli.py
odoo_mcp/server.py
odoorpc_mcp-0.1.2.dist-info/METADATA
odoorpc_mcp-0.1.2.dist-info/WHEEL
odoorpc_mcp-0.1.2.dist-info/entry_points.txt
odoorpc_mcp-0.1.2.dist-info/licenses/LICENSE
odoorpc_mcp-0.1.2.dist-info/RECORD
