Metadata-Version: 2.4
Name: odoorpc-mcp
Version: 0.1.2
Summary: MCP server that exposes Odoo database records to LLMs via Model Context Protocol
Project-URL: Homepage, https://github.com/benagricola/odoo-mcp
Project-URL: Repository, https://github.com/benagricola/odoo-mcp
Project-URL: Issues, https://github.com/benagricola/odoo-mcp/issues
Project-URL: Documentation, https://github.com/benagricola/odoo-mcp#readme
Author-email: Ben A <717328+benagricola@users.noreply.github.com>
License: MIT
License-File: LICENSE
Keywords: ai,llm,mcp,model-context-protocol,odoo
Classifier: Development Status :: 3 - Alpha
Classifier: Intended Audience :: Developers
Classifier: License :: OSI Approved :: MIT License
Classifier: Programming Language :: Python :: 3
Classifier: Programming Language :: Python :: 3.12
Classifier: Topic :: Office/Business
Classifier: Topic :: Scientific/Engineering :: Artificial Intelligence
Classifier: Topic :: Software Development :: Libraries :: Python Modules
Requires-Python: >=3.12
Requires-Dist: fastmcp>=0.6.0
Requires-Dist: odoorpc>=0.9.0
Requires-Dist: python-dotenv>=1.1.0
Provides-Extra: dev
Requires-Dist: black>=24.0.0; extra == 'dev'
Requires-Dist: pytest>=8.0.0; extra == 'dev'
Requires-Dist: ruff>=0.6.0; extra == 'dev'
